cardbin/__init__.py
cardbin/bankbin.py
cardbin/cardbin.py
cardbin-1.0.0.dist-info/AUTHORS.rst
cardbin-1.0.0.dist-info/LICENSE
cardbin-1.0.0.dist-info/METADATA
cardbin-1.0.0.dist-info/WHEEL
cardbin-1.0.0.dist-info/top_level.txt
cardbin-1.0.0.dist-info/RECORD
