Metadata-Version: 2.1
Name: cardbin
Version: 1.0.0
Summary: bankcard valid
Home-page: https://github.com/bopo/cardbin
Author: bopo.wang
Author-email: ibopo@126.com
License: MIT license
Keywords: cardbin
Platform: UNKNOWN
Classifier: Development Status :: 2 - Pre-Alpha
Classifier: Intended Audience :: Developers
Classifier: License :: OSI Approved :: MIT License
Classifier: Natural Language :: English
Classifier: Programming Language :: Python :: 2
Classifier: Programming Language :: Python :: 2.6
Classifier: Programming Language :: Python :: 2.7
Classifier: Programming Language :: Python :: 3
Classifier: Programming Language :: Python :: 3.3
Classifier: Programming Language :: Python :: 3.4
Classifier: Programming Language :: Python :: 3.5
Requires-Dist: python-stdnum
